<UnoFlipModel>
	 <turnFinished>true</turnFinished>
	 <skipTurn>false</skipTurn>
	 <skipEveryone>false</skipEveryone>
	 <turnDirection>true</turnDirection>
	 <numPlayer>3</numPlayer>
	 <chosenCardIndex>1</chosenCardIndex>
	 <currentTurn>0</currentTurn>
	 <nextPlayerIndex>1</nextPlayerIndex>
	 <status> </status>
	 <currentColour>ORANGE</currentColour>
	 <previousColour>ORANGE</previousColour>
	 <currentRank>FOUR</currentRank>
	 <previousRank>null</previousRank>
	 <topCard>
		<Card>
			<lightRank>FOUR</lightRank>
			<lightColour>RED</lightColour>
			<darkRank>FOUR</darkRank>
			<darkColour>ORANGE</darkColour>
			<side>false</side>
		</Card>
	 </topCard>
	 <isWinner>false</isWinner>
</UnoFlipModel>